neuralite/__init__.py
neuralite/interpreter.py
neuralite-0.0.3.dist-info/METADATA
neuralite-0.0.3.dist-info/WHEEL
neuralite-0.0.3.dist-info/top_level.txt
neuralite-0.0.3.dist-info/RECORD
