Metadata-Version: 2.1
Name: neuralite
Version: 0.0.3
Summary: A streamlined Python framework for rapidly building and deploying machine learning-based AIs.
Author: Dark25 (Ruben Roy)
Author-email: me@ruben-roy.com
Keywords: python,neural,machine learning,chatbots,chat,artificial intelligence,virtual assistant
Classifier: Development Status :: 3 - Alpha
Classifier: Intended Audience :: Developers
Classifier: License :: OSI Approved :: MIT License
Classifier: Programming Language :: Python :: 3
Classifier: Programming Language :: Python :: 3.6
Classifier: Programming Language :: Python :: 3.7
Classifier: Programming Language :: Python :: 3.8
Classifier: Programming Language :: Python :: 3.9
